[
    {
        "fecha_generacion": "2026-01-17 07:47:40",
        "fecha_lanzamiento": "Próximo Sorteo",
        "sorteo_objetivo": 23998,
        "juego": "LOTO3_TRICORE",
        "numeros": [
            9,
            0,
            8
        ],
        "algoritmo": "Tri-Core (RF Independiente)",
        "score_afinidad": 18,
        "nota_especial": "ESTRUCTURA_POSICIONAL"
    },
    {
        "id": 1768622690,
        "fecha_generacion": "2026-01-17 00:47:31",
        "juego": "LOTO",
        "numeros": "[6, 7, 10, 17, 29, 34]",
        "sorteo_objetivo": 5375,
        "estado": "PENDIENTE",
        "aciertos": 0,
        "score_afinidad": 5.95,
        "hora_dia": 0,
        "algoritmo": "oraculo_neural_v3",
        "nota_especial": "NORMAL",
        "fecha_lanzamiento": "18/01/2026 21:00"
    },
    {
        "id": 1768622730,
        "fecha_generacion": "2026-01-17 00:47:31",
        "juego": "LOTO3",
        "numeros": "[0, 7, 9]",
        "sorteo_objetivo": 23998,
        "estado": "PENDIENTE",
        "aciertos": 0,
        "score_afinidad": 6.1,
        "hora_dia": 0,
        "algoritmo": "oraculo_neural_v4",
        "nota_especial": "NORMAL",
        "fecha_lanzamiento": "17/01/2026 14:00"
    },
    {
        "id": 1768625737,
        "fecha_generacion": "2026-01-17 01:36:28",
        "juego": "RACHA",
        "numeros": "[1, 4, 5, 6, 7, 8, 12, 16, 17, 19]",
        "sorteo_objetivo": 10301,
        "estado": "PENDIENTE",
        "aciertos": 0,
        "score_afinidad": 4.9,
        "hora_dia": 1,
        "algoritmo": "oraculo_neural_v3",
        "nota_especial": "NORMAL",
        "fecha_lanzamiento": "17/01/2026 15:00"
    },
    {
        "id": 1768617731,
        "fecha_generacion": "2026-01-16 23:40:30",
        "juego": "LOTO",
        "numeros": "[5, 8, 11, 12, 19, 36]",
        "sorteo_objetivo": 5375,
        "estado": "PENDIENTE",
        "aciertos": 0,
        "score_afinidad": 0.0,
        "hora_dia": 23,
        "algoritmo": "gaussiano_inteligente_v1",
        "nota_especial": "NORMAL",
        "fecha_lanzamiento": "18/01/2026 21:00"
    },
    {
        "id": 1768618679,
        "fecha_generacion": "2026-01-16 23:40:30",
        "juego": "LOTO",
        "numeros": "[1, 13, 15, 29, 33, 35]",
        "sorteo_objetivo": 5375,
        "estado": "PENDIENTE",
        "aciertos": 0,
        "score_afinidad": 19.05,
        "hora_dia": 23,
        "algoritmo": "oraculo_neural_v4",
        "nota_especial": "NORMAL",
        "fecha_lanzamiento": "18/01/2026 21:00"
    },
    {
        "id": 1768626240,
        "fecha_generacion": "2026-01-17 01:58:57",
        "juego": "LOTO",
        "numeros": "[8, 21, 27, 29, 37, 39]",
        "sorteo_objetivo": 5375,
        "estado": "PENDIENTE",
        "aciertos": 0,
        "score_afinidad": 0.0,
        "hora_dia": 1,
        "algoritmo": "markov_chain_v1",
        "nota_especial": "NORMAL",
        "fecha_lanzamiento": "18/01/2026 21:00"
    },
    {
        "id": 1768618689,
        "fecha_generacion": "2026-01-16 23:40:30",
        "juego": "LOTO",
        "numeros": "[13, 22, 23, 29, 31, 35]",
        "sorteo_objetivo": 5375,
        "estado": "PENDIENTE",
        "aciertos": 0,
        "score_afinidad": 34.76,
        "hora_dia": 23,
        "algoritmo": "consenso_meritocratico_v2",
        "nota_especial": "🔥 ALTA CONFIANZA",
        "fecha_lanzamiento": "18/01/2026 21:00"
    },
    {
        "id": 1768626637,
        "fecha_generacion": "2026-01-17 01:58:57",
        "juego": "LOTO3",
        "numeros": "[1, 7, 8]",
        "sorteo_objetivo": 23998,
        "estado": "PENDIENTE",
        "aciertos": 0,
        "score_afinidad": 0.0,
        "hora_dia": 1,
        "algoritmo": "forense_biometrico_v1",
        "nota_especial": "NORMAL",
        "fecha_lanzamiento": "17/01/2026 14:00"
    },
    {
        "id": 1768618709,
        "fecha_generacion": "2026-01-16 23:40:30",
        "juego": "LOTO3",
        "numeros": "[0, 7, 8]",
        "sorteo_objetivo": 23998,
        "estado": "PENDIENTE",
        "aciertos": 0,
        "score_afinidad": 6.0,
        "hora_dia": 23,
        "algoritmo": "oraculo_neural_v4",
        "nota_especial": "NORMAL",
        "fecha_lanzamiento": "17/01/2026 14:00"
    },
    {
        "id": 1768622800,
        "fecha_generacion": "2026-01-17 00:47:31",
        "juego": "RACHA",
        "numeros": "[3, 4, 7, 8, 11, 12, 15, 16, 17, 20]",
        "sorteo_objetivo": 10301,
        "estado": "PENDIENTE",
        "aciertos": 0,
        "score_afinidad": 4.9,
        "hora_dia": 0,
        "algoritmo": "oraculo_neural_v3",
        "nota_especial": "NORMAL",
        "fecha_lanzamiento": "17/01/2026 15:00"
    },
    {
        "id": 1768621954,
        "fecha_generacion": "2026-01-17 00:47:31",
        "juego": "LOTO",
        "numeros": "[8, 21, 27, 29, 37, 39]",
        "sorteo_objetivo": 5375,
        "estado": "PENDIENTE",
        "aciertos": 0,
        "score_afinidad": 0.0,
        "hora_dia": 0,
        "algoritmo": "markov_chain_v1",
        "nota_especial": "NORMAL",
        "fecha_lanzamiento": "18/01/2026 21:00"
    },
    {
        "id": 1768618789,
        "fecha_generacion": "2026-01-16 23:40:30",
        "juego": "RACHA",
        "numeros": "[1, 2, 3, 4, 8, 13, 15, 17, 18, 19]",
        "sorteo_objetivo": 10301,
        "estado": "PENDIENTE",
        "aciertos": 0,
        "score_afinidad": 7.3,
        "hora_dia": 23,
        "algoritmo": "oraculo_neural_v4",
        "nota_especial": "NORMAL",
        "fecha_lanzamiento": "17/01/2026 15:00"
    },
    {
        "id": 1768630325,
        "fecha_generacion": "2026-01-17 02:53:26",
        "juego": "LOTO4",
        "numeros": "[1, 5, 9, 16]",
        "sorteo_objetivo": 11568,
        "estado": "PENDIENTE",
        "aciertos": 0,
        "score_afinidad": 13.45,
        "hora_dia": 2,
        "algoritmo": "oraculo_neural_v4",
        "nota_especial": "NORMAL",
        "fecha_lanzamiento": "17/01/2026 14:00"
    },
    {
        "id": 1768618630,
        "fecha_generacion": "2026-01-16 23:40:30",
        "juego": "LOTO4",
        "numeros": "[3, 8, 9, 23]",
        "sorteo_objetivo": 11568,
        "estado": "PENDIENTE",
        "aciertos": 0,
        "score_afinidad": 0.0,
        "hora_dia": 23,
        "algoritmo": "forense_biometrico_v1",
        "nota_especial": "NORMAL",
        "fecha_lanzamiento": "17/01/2026 14:00"
    },
    {
        "id": 1768627056,
        "fecha_generacion": "2026-01-17 01:58:57",
        "juego": "LOTO4",
        "numeros": "[1, 5, 9, 16]",
        "sorteo_objetivo": 11568,
        "estado": "PENDIENTE",
        "aciertos": 0,
        "score_afinidad": 13.45,
        "hora_dia": 1,
        "algoritmo": "oraculo_neural_v4",
        "nota_especial": "NORMAL",
        "fecha_lanzamiento": "17/01/2026 14:00"
    },
    {
        "id": 1768628974,
        "fecha_generacion": "2026-01-17 02:31:25",
        "juego": "LOTO3",
        "numeros": "[0, 7, 9]",
        "sorteo_objetivo": 23998,
        "estado": "PENDIENTE",
        "aciertos": 0,
        "score_afinidad": 67.94,
        "hora_dia": 2,
        "algoritmo": "consenso_meritocratico_v2",
        "nota_especial": "🔥 ALTA CONFIANZA",
        "fecha_lanzamiento": "17/01/2026 14:00"
    },
    {
        "id": 1768630335,
        "fecha_generacion": "2026-01-17 02:53:26",
        "juego": "LOTO4",
        "numeros": "[4, 5, 11, 21]",
        "sorteo_objetivo": 11568,
        "estado": "PENDIENTE",
        "aciertos": 0,
        "score_afinidad": 52.26,
        "hora_dia": 2,
        "algoritmo": "consenso_meritocratico_v2",
        "nota_especial": "🔥 ALTA CONFIANZA",
        "fecha_lanzamiento": "17/01/2026 14:00"
    },
    {
        "id": 1768625647,
        "fecha_generacion": "2026-01-17 01:36:28",
        "juego": "LOTO",
        "numeros": "[1, 23, 25, 27, 29, 33]",
        "sorteo_objetivo": 5375,
        "estado": "PENDIENTE",
        "aciertos": 0,
        "score_afinidad": 33.98,
        "hora_dia": 1,
        "algoritmo": "consenso_meritocratico_v2",
        "nota_especial": "🔥 ALTA CONFIANZA",
        "fecha_lanzamiento": "18/01/2026 21:00"
    },
    {
        "id": 1768619030,
        "fecha_generacion": "2026-01-16 23:40:30",
        "juego": "RACHA",
        "numeros": "[1, 2, 6, 7, 8, 11, 14, 15, 18, 19]",
        "sorteo_objetivo": 10301,
        "estado": "PENDIENTE",
        "aciertos": 0,
        "score_afinidad": 0.0,
        "hora_dia": 23,
        "algoritmo": "forense_biometrico_v1",
        "nota_especial": "NORMAL",
        "fecha_lanzamiento": "17/01/2026 15:00"
    },
    {
        "id": 1768617832,
        "fecha_generacion": "2026-01-16 23:40:30",
        "juego": "LOTO",
        "numeros": "[2, 14, 17, 21, 23, 24]",
        "sorteo_objetivo": 5375,
        "estado": "PENDIENTE",
        "aciertos": 0,
        "score_afinidad": 0.0,
        "hora_dia": 23,
        "algoritmo": "delta_dna_v1",
        "nota_especial": "NORMAL",
        "fecha_lanzamiento": "18/01/2026 21:00"
    },
    {
        "id": 1768618719,
        "fecha_generacion": "2026-01-16 23:40:30",
        "juego": "LOTO3",
        "numeros": "[0, 7, 8]",
        "sorteo_objetivo": 23998,
        "estado": "PENDIENTE",
        "aciertos": 0,
        "score_afinidad": 77.56,
        "hora_dia": 23,
        "algoritmo": "consenso_meritocratico_v2",
        "nota_especial": "🔥 ALTA CONFIANZA",
        "fecha_lanzamiento": "17/01/2026 14:00"
    },
    {
        "id": 1768617933,
        "fecha_generacion": "2026-01-16 23:40:30",
        "juego": "LOTO",
        "numeros": "[12, 23, 25, 28, 29, 31]",
        "sorteo_objetivo": 5375,
        "estado": "PENDIENTE",
        "aciertos": 0,
        "score_afinidad": 0.0,
        "hora_dia": 23,
        "algoritmo": "markov_chain_v1",
        "nota_especial": "NORMAL",
        "fecha_lanzamiento": "18/01/2026 21:00"
    },
    {
        "id": 1768624891,
        "fecha_generacion": "2026-01-17 01:36:28",
        "juego": "LOTO",
        "numeros": "[8, 21, 27, 29, 37, 39]",
        "sorteo_objetivo": 5375,
        "estado": "PENDIENTE",
        "aciertos": 0,
        "score_afinidad": 0.0,
        "hora_dia": 1,
        "algoritmo": "markov_chain_v1",
        "nota_especial": "NORMAL",
        "fecha_lanzamiento": "18/01/2026 21:00"
    },
    {
        "id": 1768626996,
        "fecha_generacion": "2026-01-17 01:58:57",
        "juego": "LOTO",
        "numeros": "[13, 17, 21, 27, 29, 37]",
        "sorteo_objetivo": 5375,
        "estado": "PENDIENTE",
        "aciertos": 0,
        "score_afinidad": 36.25,
        "hora_dia": 1,
        "algoritmo": "consenso_meritocratico_v2",
        "nota_especial": "🔥 ALTA CONFIANZA",
        "fecha_lanzamiento": "18/01/2026 21:00"
    },
    {
        "id": 1768618779,
        "fecha_generacion": "2026-01-16 23:40:30",
        "juego": "RACHA",
        "numeros": "[1, 2, 3, 8, 9, 12, 13, 16, 18, 19]",
        "sorteo_objetivo": 10301,
        "estado": "PENDIENTE",
        "aciertos": 0,
        "score_afinidad": 4.9,
        "hora_dia": 23,
        "algoritmo": "oraculo_neural_v3",
        "nota_especial": "NORMAL",
        "fecha_lanzamiento": "17/01/2026 15:00"
    },
    {
        "id": 1768624588,
        "fecha_generacion": "2026-01-17 01:36:28",
        "juego": "LOTO",
        "numeros": "[2, 17, 18, 20, 29, 35]",
        "sorteo_objetivo": 5375,
        "estado": "PENDIENTE",
        "aciertos": 0,
        "score_afinidad": 0.0,
        "hora_dia": 1,
        "algoritmo": "forense_biometrico_v1",
        "nota_especial": "NORMAL",
        "fecha_lanzamiento": "18/01/2026 21:00"
    },
    {
        "id": 1768630265,
        "fecha_generacion": "2026-01-17 02:53:26",
        "juego": "LOTO",
        "numeros": "[10, 13, 27, 29, 33, 37]",
        "sorteo_objetivo": 5375,
        "estado": "PENDIENTE",
        "aciertos": 0,
        "score_afinidad": 33.71,
        "hora_dia": 2,
        "algoritmo": "consenso_meritocratico_v2",
        "nota_especial": "🔥 ALTA CONFIANZA",
        "fecha_lanzamiento": "18/01/2026 21:00"
    },
    {
        "id": 1768626976,
        "fecha_generacion": "2026-01-17 01:58:57",
        "juego": "LOTO",
        "numeros": "[2, 17, 18, 21, 34, 37]",
        "sorteo_objetivo": 5375,
        "estado": "PENDIENTE",
        "aciertos": 0,
        "score_afinidad": 5.95,
        "hora_dia": 1,
        "algoritmo": "oraculo_neural_v3",
        "nota_especial": "NORMAL",
        "fecha_lanzamiento": "18/01/2026 21:00"
    },
    {
        "id": 1768625757,
        "fecha_generacion": "2026-01-17 01:36:28",
        "juego": "RACHA",
        "numeros": "[1, 4, 5, 6, 8, 12, 14, 17, 19, 20]",
        "sorteo_objetivo": 10301,
        "estado": "PENDIENTE",
        "aciertos": 0,
        "score_afinidad": 69.32,
        "hora_dia": 1,
        "algoritmo": "consenso_meritocratico_v2",
        "nota_especial": "🔥 ALTA CONFIANZA",
        "fecha_lanzamiento": "17/01/2026 15:00"
    },
    {
        "id": 1768628924,
        "fecha_generacion": "2026-01-17 02:31:25",
        "juego": "LOTO",
        "numeros": "[1, 13, 14, 16, 22, 41]",
        "sorteo_objetivo": 5375,
        "estado": "PENDIENTE",
        "aciertos": 0,
        "score_afinidad": 6.35,
        "hora_dia": 2,
        "algoritmo": "oraculo_neural_v3",
        "nota_especial": "NORMAL",
        "fecha_lanzamiento": "18/01/2026 21:00"
    },
    {
        "id": 1768621651,
        "fecha_generacion": "2026-01-17 00:47:31",
        "juego": "LOTO",
        "numeros": "[2, 19, 21, 30, 31, 38]",
        "sorteo_objetivo": 5375,
        "estado": "PENDIENTE",
        "aciertos": 0,
        "score_afinidad": 0.0,
        "hora_dia": 0,
        "algoritmo": "forense_biometrico_v1",
        "nota_especial": "NORMAL",
        "fecha_lanzamiento": "18/01/2026 21:00"
    },
    {
        "id": 1768630255,
        "fecha_generacion": "2026-01-17 02:53:26",
        "juego": "LOTO",
        "numeros": "[1, 13, 15, 29, 33, 35]",
        "sorteo_objetivo": 5375,
        "estado": "PENDIENTE",
        "aciertos": 0,
        "score_afinidad": 19.05,
        "hora_dia": 2,
        "algoritmo": "oraculo_neural_v4",
        "nota_especial": "NORMAL",
        "fecha_lanzamiento": "18/01/2026 21:00"
    },
    {
        "id": 1768630355,
        "fecha_generacion": "2026-01-17 02:53:26",
        "juego": "RACHA",
        "numeros": "[5, 6, 7, 8, 9, 10, 12, 14, 17, 19]",
        "sorteo_objetivo": 10301,
        "estado": "PENDIENTE",
        "aciertos": 0,
        "score_afinidad": 4.9,
        "hora_dia": 2,
        "algoritmo": "oraculo_neural_v3",
        "nota_especial": "NORMAL",
        "fecha_lanzamiento": "17/01/2026 15:00"
    },
    {
        "id": 1768624689,
        "fecha_generacion": "2026-01-17 01:36:28",
        "juego": "LOTO",
        "numeros": "[7, 19, 26, 32, 40, 41]",
        "sorteo_objetivo": 5375,
        "estado": "PENDIENTE",
        "aciertos": 0,
        "score_afinidad": 0.0,
        "hora_dia": 1,
        "algoritmo": "gaussiano_inteligente_v1",
        "nota_especial": "NORMAL",
        "fecha_lanzamiento": "18/01/2026 21:00"
    },
    {
        "id": 1768622760,
        "fecha_generacion": "2026-01-17 00:47:31",
        "juego": "LOTO4",
        "numeros": "[1, 11, 19, 20]",
        "sorteo_objetivo": 11568,
        "estado": "PENDIENTE",
        "aciertos": 0,
        "score_afinidad": 3.25,
        "hora_dia": 0,
        "algoritmo": "oraculo_neural_v3",
        "nota_especial": "NORMAL",
        "fecha_lanzamiento": "17/01/2026 14:00"
    },
    {
        "id": 1768622770,
        "fecha_generacion": "2026-01-17 00:47:31",
        "juego": "LOTO4",
        "numeros": "[1, 5, 9, 16]",
        "sorteo_objetivo": 11568,
        "estado": "PENDIENTE",
        "aciertos": 0,
        "score_afinidad": 13.45,
        "hora_dia": 0,
        "algoritmo": "oraculo_neural_v4",
        "nota_especial": "NORMAL",
        "fecha_lanzamiento": "17/01/2026 14:00"
    },
    {
        "id": 1768625988,
        "fecha_generacion": "2026-01-17 01:36:28",
        "juego": "RACHA",
        "numeros": "[1, 2, 3, 6, 7, 9, 14, 18, 19, 20]",
        "sorteo_objetivo": 10301,
        "estado": "PENDIENTE",
        "aciertos": 0,
        "score_afinidad": 0.0,
        "hora_dia": 1,
        "algoritmo": "forense_biometrico_v1",
        "nota_especial": "NORMAL",
        "fecha_lanzamiento": "17/01/2026 15:00"
    },
    {
        "id": 1768618759,
        "fecha_generacion": "2026-01-16 23:40:30",
        "juego": "LOTO4",
        "numeros": "[1, 5, 9, 16]",
        "sorteo_objetivo": 11568,
        "estado": "PENDIENTE",
        "aciertos": 0,
        "score_afinidad": 39.13,
        "hora_dia": 23,
        "algoritmo": "consenso_meritocratico_v2",
        "nota_especial": "🔥 ALTA CONFIANZA",
        "fecha_lanzamiento": "17/01/2026 14:00"
    },
    {
        "id": 1768618799,
        "fecha_generacion": "2026-01-16 23:40:30",
        "juego": "RACHA",
        "numeros": "[1, 2, 3, 4, 8, 13, 16, 17, 18, 19]",
        "sorteo_objetivo": 10301,
        "estado": "PENDIENTE",
        "aciertos": 0,
        "score_afinidad": 73.22,
        "hora_dia": 23,
        "algoritmo": "consenso_meritocratico_v2",
        "nota_especial": "🔥 ALTA CONFIANZA",
        "fecha_lanzamiento": "17/01/2026 15:00"
    },
    {
        "id": 1768627096,
        "fecha_generacion": "2026-01-17 01:58:57",
        "juego": "RACHA",
        "numeros": "[1, 2, 3, 4, 8, 13, 15, 17, 18, 19]",
        "sorteo_objetivo": 10301,
        "estado": "PENDIENTE",
        "aciertos": 0,
        "score_afinidad": 7.3,
        "hora_dia": 1,
        "algoritmo": "oraculo_neural_v4",
        "nota_especial": "NORMAL",
        "fecha_lanzamiento": "17/01/2026 15:00"
    },
    {
        "id": 1768629307,
        "fecha_generacion": "2026-01-17 02:53:26",
        "juego": "LOTO",
        "numeros": "[7, 20, 30, 32, 33, 37]",
        "sorteo_objetivo": 5375,
        "estado": "PENDIENTE",
        "aciertos": 0,
        "score_afinidad": 0.0,
        "hora_dia": 2,
        "algoritmo": "gaussiano_inteligente_v1",
        "nota_especial": "NORMAL",
        "fecha_lanzamiento": "18/01/2026 21:00"
    },
    {
        "id": 1768630295,
        "fecha_generacion": "2026-01-17 02:53:26",
        "juego": "LOTO3",
        "numeros": "[0, 7, 9]",
        "sorteo_objetivo": 23998,
        "estado": "PENDIENTE",
        "aciertos": 0,
        "score_afinidad": 71.14,
        "hora_dia": 2,
        "algoritmo": "consenso_meritocratico_v2",
        "nota_especial": "🔥 ALTA CONFIANZA",
        "fecha_lanzamiento": "17/01/2026 14:00"
    },
    {
        "id": 1768625637,
        "fecha_generacion": "2026-01-17 01:36:28",
        "juego": "LOTO",
        "numeros": "[1, 13, 15, 29, 33, 35]",
        "sorteo_objetivo": 5375,
        "estado": "PENDIENTE",
        "aciertos": 0,
        "score_afinidad": 19.05,
        "hora_dia": 1,
        "algoritmo": "oraculo_neural_v4",
        "nota_especial": "NORMAL",
        "fecha_lanzamiento": "18/01/2026 21:00"
    },
    {
        "id": 1768628964,
        "fecha_generacion": "2026-01-17 02:31:25",
        "juego": "LOTO3",
        "numeros": "[0, 7, 9]",
        "sorteo_objetivo": 23998,
        "estado": "PENDIENTE",
        "aciertos": 0,
        "score_afinidad": 6.1,
        "hora_dia": 2,
        "algoritmo": "oraculo_neural_v4",
        "nota_especial": "NORMAL",
        "fecha_lanzamiento": "17/01/2026 14:00"
    },
    {
        "id": 1768630375,
        "fecha_generacion": "2026-01-17 02:53:26",
        "juego": "RACHA",
        "numeros": "[1, 4, 5, 7, 8, 9, 13, 15, 17, 19]",
        "sorteo_objetivo": 10301,
        "estado": "PENDIENTE",
        "aciertos": 0,
        "score_afinidad": 63.9,
        "hora_dia": 2,
        "algoritmo": "consenso_meritocratico_v2",
        "nota_especial": "🔥 ALTA CONFIANZA",
        "fecha_lanzamiento": "17/01/2026 15:00"
    },
    {
        "id": 1768618749,
        "fecha_generacion": "2026-01-16 23:40:30",
        "juego": "LOTO4",
        "numeros": "[1, 5, 9, 16]",
        "sorteo_objetivo": 11568,
        "estado": "PENDIENTE",
        "aciertos": 0,
        "score_afinidad": 13.45,
        "hora_dia": 23,
        "algoritmo": "oraculo_neural_v4",
        "nota_especial": "NORMAL",
        "fecha_lanzamiento": "17/01/2026 14:00"
    },
    {
        "id": 1768626139,
        "fecha_generacion": "2026-01-17 01:58:57",
        "juego": "LOTO",
        "numeros": "[3, 7, 24, 28, 29, 32]",
        "sorteo_objetivo": 5375,
        "estado": "PENDIENTE",
        "aciertos": 0,
        "score_afinidad": 0.0,
        "hora_dia": 1,
        "algoritmo": "delta_dna_v1",
        "nota_especial": "NORMAL",
        "fecha_lanzamiento": "18/01/2026 21:00"
    },
    {
        "id": 1768623051,
        "fecha_generacion": "2026-01-17 00:47:31",
        "juego": "RACHA",
        "numeros": "[2, 3, 7, 8, 9, 12, 15, 18, 19, 20]",
        "sorteo_objetivo": 10301,
        "estado": "PENDIENTE",
        "aciertos": 0,
        "score_afinidad": 0.0,
        "hora_dia": 0,
        "algoritmo": "forense_biometrico_v1",
        "nota_especial": "NORMAL",
        "fecha_lanzamiento": "17/01/2026 15:00"
    },
    {
        "id": 1768627046,
        "fecha_generacion": "2026-01-17 01:58:57",
        "juego": "LOTO4",
        "numeros": "[9, 11, 19, 20]",
        "sorteo_objetivo": 11568,
        "estado": "PENDIENTE",
        "aciertos": 0,
        "score_afinidad": 3.25,
        "hora_dia": 1,
        "algoritmo": "oraculo_neural_v3",
        "nota_especial": "NORMAL",
        "fecha_lanzamiento": "17/01/2026 14:00"
    },
    {
        "id": 1768629906,
        "fecha_generacion": "2026-01-17 02:53:26",
        "juego": "LOTO3",
        "numeros": "[4, 7, 8]",
        "sorteo_objetivo": 23998,
        "estado": "PENDIENTE",
        "aciertos": 0,
        "score_afinidad": 0.0,
        "hora_dia": 2,
        "algoritmo": "forense_biometrico_v1",
        "nota_especial": "NORMAL",
        "fecha_lanzamiento": "17/01/2026 14:00"
    },
    {
        "id": 1768618739,
        "fecha_generacion": "2026-01-16 23:40:30",
        "juego": "LOTO4",
        "numeros": "[7, 8, 19, 21]",
        "sorteo_objetivo": 11568,
        "estado": "PENDIENTE",
        "aciertos": 0,
        "score_afinidad": 3.25,
        "hora_dia": 23,
        "algoritmo": "oraculo_neural_v3",
        "nota_especial": "NORMAL",
        "fecha_lanzamiento": "17/01/2026 14:00"
    },
    {
        "id": 1768627106,
        "fecha_generacion": "2026-01-17 01:58:57",
        "juego": "RACHA",
        "numeros": "[1, 2, 4, 8, 9, 13, 14, 15, 17, 19]",
        "sorteo_objetivo": 10301,
        "estado": "PENDIENTE",
        "aciertos": 0,
        "score_afinidad": 67.78,
        "hora_dia": 1,
        "algoritmo": "consenso_meritocratico_v2",
        "nota_especial": "🔥 ALTA CONFIANZA",
        "fecha_lanzamiento": "17/01/2026 15:00"
    },
    {
        "id": 1768628994,
        "fecha_generacion": "2026-01-17 02:31:25",
        "juego": "LOTO4",
        "numeros": "[6, 7, 11, 21]",
        "sorteo_objetivo": 11568,
        "estado": "PENDIENTE",
        "aciertos": 0,
        "score_afinidad": 3.25,
        "hora_dia": 2,
        "algoritmo": "oraculo_neural_v3",
        "nota_especial": "NORMAL",
        "fecha_lanzamiento": "17/01/2026 14:00"
    },
    {
        "id": 1768629408,
        "fecha_generacion": "2026-01-17 02:53:26",
        "juego": "LOTO",
        "numeros": "[7, 11, 19, 20, 26, 36]",
        "sorteo_objetivo": 5375,
        "estado": "PENDIENTE",
        "aciertos": 0,
        "score_afinidad": 0.0,
        "hora_dia": 2,
        "algoritmo": "delta_dna_v1",
        "nota_especial": "NORMAL",
        "fecha_lanzamiento": "18/01/2026 21:00"
    },
    {
        "id": 1768626937,
        "fecha_generacion": "2026-01-17 01:58:57",
        "juego": "LOTO4",
        "numeros": "[5, 9, 16, 17]",
        "sorteo_objetivo": 11568,
        "estado": "PENDIENTE",
        "aciertos": 0,
        "score_afinidad": 0.0,
        "hora_dia": 1,
        "algoritmo": "forense_biometrico_v1",
        "nota_especial": "NORMAL",
        "fecha_lanzamiento": "17/01/2026 14:00"
    },
    {
        "id": 1768617630,
        "fecha_generacion": "2026-01-16 23:40:30",
        "juego": "LOTO",
        "numeros": "[2, 11, 14, 15, 31, 34]",
        "sorteo_objetivo": 5375,
        "estado": "PENDIENTE",
        "aciertos": 0,
        "score_afinidad": 0.0,
        "hora_dia": 23,
        "algoritmo": "forense_biometrico_v1",
        "nota_especial": "NORMAL",
        "fecha_lanzamiento": "18/01/2026 21:00"
    },
    {
        "id": 1768629206,
        "fecha_generacion": "2026-01-17 02:53:26",
        "juego": "LOTO",
        "numeros": "[14, 19, 27, 28, 31, 38]",
        "sorteo_objetivo": 5375,
        "estado": "PENDIENTE",
        "aciertos": 0,
        "score_afinidad": 0.0,
        "hora_dia": 2,
        "algoritmo": "forense_biometrico_v1",
        "nota_especial": "NORMAL",
        "fecha_lanzamiento": "18/01/2026 21:00"
    },
    {
        "id": 1768622651,
        "fecha_generacion": "2026-01-17 00:47:31",
        "juego": "LOTO4",
        "numeros": "[3, 7, 20, 21]",
        "sorteo_objetivo": 11568,
        "estado": "PENDIENTE",
        "aciertos": 0,
        "score_afinidad": 0.0,
        "hora_dia": 0,
        "algoritmo": "forense_biometrico_v1",
        "nota_especial": "NORMAL",
        "fecha_lanzamiento": "17/01/2026 14:00"
    },
    {
        "id": 1768629034,
        "fecha_generacion": "2026-01-17 02:31:25",
        "juego": "RACHA",
        "numeros": "[1, 2, 3, 8, 9, 14, 16, 17, 19, 20]",
        "sorteo_objetivo": 10301,
        "estado": "PENDIENTE",
        "aciertos": 0,
        "score_afinidad": 4.9,
        "hora_dia": 2,
        "algoritmo": "oraculo_neural_v3",
        "nota_especial": "NORMAL",
        "fecha_lanzamiento": "17/01/2026 15:00"
    },
    {
        "id": 1768622780,
        "fecha_generacion": "2026-01-17 00:47:31",
        "juego": "LOTO4",
        "numeros": "[1, 9, 11, 19]",
        "sorteo_objetivo": 11568,
        "estado": "PENDIENTE",
        "aciertos": 0,
        "score_afinidad": 53.62,
        "hora_dia": 0,
        "algoritmo": "consenso_meritocratico_v2",
        "nota_especial": "🔥 ALTA CONFIANZA",
        "fecha_lanzamiento": "17/01/2026 14:00"
    },
    {
        "id": 1768628944,
        "fecha_generacion": "2026-01-17 02:31:25",
        "juego": "LOTO",
        "numeros": "[1, 8, 13, 22, 27, 29]",
        "sorteo_objetivo": 5375,
        "estado": "PENDIENTE",
        "aciertos": 0,
        "score_afinidad": 31.26,
        "hora_dia": 2,
        "algoritmo": "consenso_meritocratico_v2",
        "nota_especial": "🔥 ALTA CONFIANZA",
        "fecha_lanzamiento": "18/01/2026 21:00"
    },
    {
        "id": 1768622700,
        "fecha_generacion": "2026-01-17 00:47:31",
        "juego": "LOTO",
        "numeros": "[1, 13, 15, 29, 33, 35]",
        "sorteo_objetivo": 5375,
        "estado": "PENDIENTE",
        "aciertos": 0,
        "score_afinidad": 19.05,
        "hora_dia": 0,
        "algoritmo": "oraculo_neural_v4",
        "nota_especial": "NORMAL",
        "fecha_lanzamiento": "18/01/2026 21:00"
    },
    {
        "id": 1768622810,
        "fecha_generacion": "2026-01-17 00:47:31",
        "juego": "RACHA",
        "numeros": "[1, 2, 3, 4, 8, 13, 15, 17, 18, 19]",
        "sorteo_objetivo": 10301,
        "estado": "PENDIENTE",
        "aciertos": 0,
        "score_afinidad": 7.3,
        "hora_dia": 0,
        "algoritmo": "oraculo_neural_v4",
        "nota_especial": "NORMAL",
        "fecha_lanzamiento": "17/01/2026 15:00"
    },
    {
        "id": 1768629044,
        "fecha_generacion": "2026-01-17 02:31:25",
        "juego": "RACHA",
        "numeros": "[1, 2, 3, 4, 8, 13, 15, 17, 18, 19]",
        "sorteo_objetivo": 10301,
        "estado": "PENDIENTE",
        "aciertos": 0,
        "score_afinidad": 7.3,
        "hora_dia": 2,
        "algoritmo": "oraculo_neural_v4",
        "nota_especial": "NORMAL",
        "fecha_lanzamiento": "17/01/2026 15:00"
    },
    {
        "id": 1768629014,
        "fecha_generacion": "2026-01-17 02:31:25",
        "juego": "LOTO4",
        "numeros": "[1, 6, 7, 21]",
        "sorteo_objetivo": 11568,
        "estado": "PENDIENTE",
        "aciertos": 0,
        "score_afinidad": 45.66,
        "hora_dia": 2,
        "algoritmo": "consenso_meritocratico_v2",
        "nota_especial": "🔥 ALTA CONFIANZA",
        "fecha_lanzamiento": "17/01/2026 14:00"
    },
    {
        "id": 1768628087,
        "fecha_generacion": "2026-01-17 02:31:25",
        "juego": "LOTO",
        "numeros": "[13, 19, 24, 29, 30, 34]",
        "sorteo_objetivo": 5375,
        "estado": "PENDIENTE",
        "aciertos": 0,
        "score_afinidad": 0.0,
        "hora_dia": 2,
        "algoritmo": "delta_dna_v1",
        "nota_especial": "NORMAL",
        "fecha_lanzamiento": "18/01/2026 21:00"
    },
    {
        "id": 1768629509,
        "fecha_generacion": "2026-01-17 02:53:26",
        "juego": "LOTO",
        "numeros": "[8, 21, 27, 29, 37, 39]",
        "sorteo_objetivo": 5375,
        "estado": "PENDIENTE",
        "aciertos": 0,
        "score_afinidad": 0.0,
        "hora_dia": 2,
        "algoritmo": "markov_chain_v1",
        "nota_especial": "NORMAL",
        "fecha_lanzamiento": "18/01/2026 21:00"
    },
    {
        "id": 1768630315,
        "fecha_generacion": "2026-01-17 02:53:26",
        "juego": "LOTO4",
        "numeros": "[4, 5, 11, 21]",
        "sorteo_objetivo": 11568,
        "estado": "PENDIENTE",
        "aciertos": 0,
        "score_afinidad": 3.25,
        "hora_dia": 2,
        "algoritmo": "oraculo_neural_v3",
        "nota_especial": "NORMAL",
        "fecha_lanzamiento": "17/01/2026 14:00"
    },
    {
        "id": 1768625717,
        "fecha_generacion": "2026-01-17 01:36:28",
        "juego": "LOTO4",
        "numeros": "[5, 9, 12, 13]",
        "sorteo_objetivo": 11568,
        "estado": "PENDIENTE",
        "aciertos": 0,
        "score_afinidad": 49.15,
        "hora_dia": 1,
        "algoritmo": "consenso_meritocratico_v2",
        "nota_especial": "🔥 ALTA CONFIANZA",
        "fecha_lanzamiento": "17/01/2026 14:00"
    },
    {
        "id": 1768627026,
        "fecha_generacion": "2026-01-17 01:58:57",
        "juego": "LOTO3",
        "numeros": "[0, 7, 9]",
        "sorteo_objetivo": 23998,
        "estado": "PENDIENTE",
        "aciertos": 0,
        "score_afinidad": 58.32,
        "hora_dia": 1,
        "algoritmo": "consenso_meritocratico_v2",
        "nota_especial": "🔥 ALTA CONFIANZA",
        "fecha_lanzamiento": "17/01/2026 14:00"
    },
    {
        "id": 1768622820,
        "fecha_generacion": "2026-01-17 00:47:31",
        "juego": "RACHA",
        "numeros": "[3, 4, 7, 8, 12, 13, 15, 16, 17, 20]",
        "sorteo_objetivo": 10301,
        "estado": "PENDIENTE",
        "aciertos": 0,
        "score_afinidad": 69.56,
        "hora_dia": 0,
        "algoritmo": "consenso_meritocratico_v2",
        "nota_especial": "🔥 ALTA CONFIANZA",
        "fecha_lanzamiento": "17/01/2026 15:00"
    },
    {
        "id": 1768627016,
        "fecha_generacion": "2026-01-17 01:58:57",
        "juego": "LOTO3",
        "numeros": "[0, 7, 9]",
        "sorteo_objetivo": 23998,
        "estado": "PENDIENTE",
        "aciertos": 0,
        "score_afinidad": 6.1,
        "hora_dia": 1,
        "algoritmo": "oraculo_neural_v4",
        "nota_especial": "NORMAL",
        "fecha_lanzamiento": "17/01/2026 14:00"
    },
    {
        "id": 1768628885,
        "fecha_generacion": "2026-01-17 02:31:25",
        "juego": "LOTO4",
        "numeros": "[7, 8, 11, 18]",
        "sorteo_objetivo": 11568,
        "estado": "PENDIENTE",
        "aciertos": 0,
        "score_afinidad": 0.0,
        "hora_dia": 2,
        "algoritmo": "forense_biometrico_v1",
        "nota_especial": "NORMAL",
        "fecha_lanzamiento": "17/01/2026 14:00"
    },
    {
        "id": 1768630606,
        "fecha_generacion": "2026-01-17 02:53:26",
        "juego": "RACHA",
        "numeros": "[3, 5, 6, 7, 9, 13, 14, 16, 17, 18]",
        "sorteo_objetivo": 10301,
        "estado": "PENDIENTE",
        "aciertos": 0,
        "score_afinidad": 0.0,
        "hora_dia": 2,
        "algoritmo": "forense_biometrico_v1",
        "nota_especial": "NORMAL",
        "fecha_lanzamiento": "17/01/2026 15:00"
    },
    {
        "id": 1768630206,
        "fecha_generacion": "2026-01-17 02:53:26",
        "juego": "LOTO4",
        "numeros": "[3, 7, 14, 15]",
        "sorteo_objetivo": 11568,
        "estado": "PENDIENTE",
        "aciertos": 0,
        "score_afinidad": 0.0,
        "hora_dia": 2,
        "algoritmo": "forense_biometrico_v1",
        "nota_especial": "NORMAL",
        "fecha_lanzamiento": "17/01/2026 14:00"
    },
    {
        "id": 1768626986,
        "fecha_generacion": "2026-01-17 01:58:57",
        "juego": "LOTO",
        "numeros": "[1, 13, 15, 29, 33, 35]",
        "sorteo_objetivo": 5375,
        "estado": "PENDIENTE",
        "aciertos": 0,
        "score_afinidad": 19.05,
        "hora_dia": 1,
        "algoritmo": "oraculo_neural_v4",
        "nota_especial": "NORMAL",
        "fecha_lanzamiento": "18/01/2026 21:00"
    },
    {
        "id": 1768624790,
        "fecha_generacion": "2026-01-17 01:36:28",
        "juego": "LOTO",
        "numeros": "[13, 17, 26, 31, 32, 34]",
        "sorteo_objetivo": 5375,
        "estado": "PENDIENTE",
        "aciertos": 0,
        "score_afinidad": 0.0,
        "hora_dia": 1,
        "algoritmo": "delta_dna_v1",
        "nota_especial": "NORMAL",
        "fecha_lanzamiento": "18/01/2026 21:00"
    },
    {
        "id": 1768621752,
        "fecha_generacion": "2026-01-17 00:47:31",
        "juego": "LOTO",
        "numeros": "[2, 19, 24, 29, 39, 40]",
        "sorteo_objetivo": 5375,
        "estado": "PENDIENTE",
        "aciertos": 0,
        "score_afinidad": 0.0,
        "hora_dia": 0,
        "algoritmo": "gaussiano_inteligente_v1",
        "nota_especial": "NORMAL",
        "fecha_lanzamiento": "18/01/2026 21:00"
    },
    {
        "id": 1768628585,
        "fecha_generacion": "2026-01-17 02:31:25",
        "juego": "LOTO3",
        "numeros": "[1, 7, 8]",
        "sorteo_objetivo": 23998,
        "estado": "PENDIENTE",
        "aciertos": 0,
        "score_afinidad": 0.0,
        "hora_dia": 2,
        "algoritmo": "forense_biometrico_v1",
        "nota_especial": "NORMAL",
        "fecha_lanzamiento": "17/01/2026 14:00"
    },
    {
        "id": 1768625697,
        "fecha_generacion": "2026-01-17 01:36:28",
        "juego": "LOTO4",
        "numeros": "[9, 12, 13, 23]",
        "sorteo_objetivo": 11568,
        "estado": "PENDIENTE",
        "aciertos": 0,
        "score_afinidad": 3.25,
        "hora_dia": 1,
        "algoritmo": "oraculo_neural_v3",
        "nota_especial": "NORMAL",
        "fecha_lanzamiento": "17/01/2026 14:00"
    },
    {
        "id": 1768627066,
        "fecha_generacion": "2026-01-17 01:58:57",
        "juego": "LOTO4",
        "numeros": "[9, 11, 19, 20]",
        "sorteo_objetivo": 11568,
        "estado": "PENDIENTE",
        "aciertos": 0,
        "score_afinidad": 55.23,
        "hora_dia": 1,
        "algoritmo": "consenso_meritocratico_v2",
        "nota_especial": "🔥 ALTA CONFIANZA",
        "fecha_lanzamiento": "17/01/2026 14:00"
    },
    {
        "id": 1768627986,
        "fecha_generacion": "2026-01-17 02:31:25",
        "juego": "LOTO",
        "numeros": "[4, 7, 11, 12, 34, 41]",
        "sorteo_objetivo": 5375,
        "estado": "PENDIENTE",
        "aciertos": 0,
        "score_afinidad": 0.0,
        "hora_dia": 2,
        "algoritmo": "gaussiano_inteligente_v1",
        "nota_especial": "NORMAL",
        "fecha_lanzamiento": "18/01/2026 21:00"
    },
    {
        "id": 1768622710,
        "fecha_generacion": "2026-01-17 00:47:31",
        "juego": "LOTO",
        "numeros": "[7, 10, 27, 29, 35, 37]",
        "sorteo_objetivo": 5375,
        "estado": "PENDIENTE",
        "aciertos": 0,
        "score_afinidad": 33.98,
        "hora_dia": 0,
        "algoritmo": "consenso_meritocratico_v2",
        "nota_especial": "🔥 ALTA CONFIANZA",
        "fecha_lanzamiento": "18/01/2026 21:00"
    },
    {
        "id": 1768618330,
        "fecha_generacion": "2026-01-16 23:40:30",
        "juego": "LOTO3",
        "numeros": "[1, 4, 5]",
        "sorteo_objetivo": 23998,
        "estado": "PENDIENTE",
        "aciertos": 0,
        "score_afinidad": 0.0,
        "hora_dia": 23,
        "algoritmo": "forense_biometrico_v1",
        "nota_especial": "NORMAL",
        "fecha_lanzamiento": "17/01/2026 14:00"
    },
    {
        "id": 1768621853,
        "fecha_generacion": "2026-01-17 00:47:31",
        "juego": "LOTO",
        "numeros": "[17, 18, 22, 29, 37, 40]",
        "sorteo_objetivo": 5375,
        "estado": "PENDIENTE",
        "aciertos": 0,
        "score_afinidad": 0.0,
        "hora_dia": 0,
        "algoritmo": "delta_dna_v1",
        "nota_especial": "NORMAL",
        "fecha_lanzamiento": "18/01/2026 21:00"
    },
    {
        "id": 1768625937,
        "fecha_generacion": "2026-01-17 01:58:57",
        "juego": "LOTO",
        "numeros": "[10, 18, 19, 23, 29, 36]",
        "sorteo_objetivo": 5375,
        "estado": "PENDIENTE",
        "aciertos": 0,
        "score_afinidad": 0.0,
        "hora_dia": 1,
        "algoritmo": "forense_biometrico_v1",
        "nota_especial": "NORMAL",
        "fecha_lanzamiento": "18/01/2026 21:00"
    },
    {
        "id": 1768625288,
        "fecha_generacion": "2026-01-17 01:36:28",
        "juego": "LOTO3",
        "numeros": "[0, 1, 7]",
        "sorteo_objetivo": 23998,
        "estado": "PENDIENTE",
        "aciertos": 0,
        "score_afinidad": 0.0,
        "hora_dia": 1,
        "algoritmo": "forense_biometrico_v1",
        "nota_especial": "NORMAL",
        "fecha_lanzamiento": "17/01/2026 14:00"
    },
    {
        "id": 1768622740,
        "fecha_generacion": "2026-01-17 00:47:31",
        "juego": "LOTO3",
        "numeros": "[0, 7, 9]",
        "sorteo_objetivo": 23998,
        "estado": "PENDIENTE",
        "aciertos": 0,
        "score_afinidad": 61.53,
        "hora_dia": 0,
        "algoritmo": "consenso_meritocratico_v2",
        "nota_especial": "🔥 ALTA CONFIANZA",
        "fecha_lanzamiento": "17/01/2026 14:00"
    },
    {
        "id": 1768627885,
        "fecha_generacion": "2026-01-17 02:31:25",
        "juego": "LOTO",
        "numeros": "[3, 8, 11, 28, 29, 34]",
        "sorteo_objetivo": 5375,
        "estado": "PENDIENTE",
        "aciertos": 0,
        "score_afinidad": 0.0,
        "hora_dia": 2,
        "algoritmo": "forense_biometrico_v1",
        "nota_especial": "NORMAL",
        "fecha_lanzamiento": "18/01/2026 21:00"
    },
    {
        "id": 1768628188,
        "fecha_generacion": "2026-01-17 02:31:25",
        "juego": "LOTO",
        "numeros": "[8, 21, 27, 29, 37, 39]",
        "sorteo_objetivo": 5375,
        "estado": "PENDIENTE",
        "aciertos": 0,
        "score_afinidad": 0.0,
        "hora_dia": 2,
        "algoritmo": "markov_chain_v1",
        "nota_especial": "NORMAL",
        "fecha_lanzamiento": "18/01/2026 21:00"
    },
    {
        "id": 1768625667,
        "fecha_generacion": "2026-01-17 01:36:28",
        "juego": "LOTO3",
        "numeros": "[0, 7, 9]",
        "sorteo_objetivo": 23998,
        "estado": "PENDIENTE",
        "aciertos": 0,
        "score_afinidad": 6.1,
        "hora_dia": 1,
        "algoritmo": "oraculo_neural_v4",
        "nota_especial": "NORMAL",
        "fecha_lanzamiento": "17/01/2026 14:00"
    },
    {
        "id": 1768629004,
        "fecha_generacion": "2026-01-17 02:31:25",
        "juego": "LOTO4",
        "numeros": "[1, 5, 9, 16]",
        "sorteo_objetivo": 11568,
        "estado": "PENDIENTE",
        "aciertos": 0,
        "score_afinidad": 13.45,
        "hora_dia": 2,
        "algoritmo": "oraculo_neural_v4",
        "nota_especial": "NORMAL",
        "fecha_lanzamiento": "17/01/2026 14:00"
    },
    {
        "id": 1768628934,
        "fecha_generacion": "2026-01-17 02:31:25",
        "juego": "LOTO",
        "numeros": "[1, 13, 15, 29, 33, 35]",
        "sorteo_objetivo": 5375,
        "estado": "PENDIENTE",
        "aciertos": 0,
        "score_afinidad": 19.05,
        "hora_dia": 2,
        "algoritmo": "oraculo_neural_v4",
        "nota_especial": "NORMAL",
        "fecha_lanzamiento": "18/01/2026 21:00"
    },
    {
        "id": 1768629054,
        "fecha_generacion": "2026-01-17 02:31:25",
        "juego": "RACHA",
        "numeros": "[1, 2, 3, 8, 9, 14, 15, 17, 19, 20]",
        "sorteo_objetivo": 10301,
        "estado": "PENDIENTE",
        "aciertos": 0,
        "score_afinidad": 73.41,
        "hora_dia": 2,
        "algoritmo": "consenso_meritocratico_v2",
        "nota_especial": "🔥 ALTA CONFIANZA",
        "fecha_lanzamiento": "17/01/2026 15:00"
    },
    {
        "id": 1768625707,
        "fecha_generacion": "2026-01-17 01:36:28",
        "juego": "LOTO4",
        "numeros": "[1, 5, 9, 16]",
        "sorteo_objetivo": 11568,
        "estado": "PENDIENTE",
        "aciertos": 0,
        "score_afinidad": 13.45,
        "hora_dia": 1,
        "algoritmo": "oraculo_neural_v4",
        "nota_especial": "NORMAL",
        "fecha_lanzamiento": "17/01/2026 14:00"
    },
    {
        "id": 1768627337,
        "fecha_generacion": "2026-01-17 01:58:57",
        "juego": "RACHA",
        "numeros": "[2, 6, 7, 9, 11, 12, 13, 14, 19, 20]",
        "sorteo_objetivo": 10301,
        "estado": "PENDIENTE",
        "aciertos": 0,
        "score_afinidad": 0.0,
        "hora_dia": 1,
        "algoritmo": "forense_biometrico_v1",
        "nota_especial": "NORMAL",
        "fecha_lanzamiento": "17/01/2026 15:00"
    },
    {
        "id": 1768625588,
        "fecha_generacion": "2026-01-17 01:36:28",
        "juego": "LOTO4",
        "numeros": "[3, 7, 20, 21]",
        "sorteo_objetivo": 11568,
        "estado": "PENDIENTE",
        "aciertos": 0,
        "score_afinidad": 0.0,
        "hora_dia": 1,
        "algoritmo": "forense_biometrico_v1",
        "nota_especial": "NORMAL",
        "fecha_lanzamiento": "17/01/2026 14:00"
    },
    {
        "id": 1768627086,
        "fecha_generacion": "2026-01-17 01:58:57",
        "juego": "RACHA",
        "numeros": "[2, 4, 5, 6, 9, 12, 13, 14, 15, 17]",
        "sorteo_objetivo": 10301,
        "estado": "PENDIENTE",
        "aciertos": 0,
        "score_afinidad": 4.9,
        "hora_dia": 1,
        "algoritmo": "oraculo_neural_v3",
        "nota_especial": "NORMAL",
        "fecha_lanzamiento": "17/01/2026 15:00"
    },
    {
        "id": 1768629285,
        "fecha_generacion": "2026-01-17 02:31:25",
        "juego": "RACHA",
        "numeros": "[2, 3, 4, 6, 7, 9, 15, 16, 18, 19]",
        "sorteo_objetivo": 10301,
        "estado": "PENDIENTE",
        "aciertos": 0,
        "score_afinidad": 0.0,
        "hora_dia": 2,
        "algoritmo": "forense_biometrico_v1",
        "nota_especial": "NORMAL",
        "fecha_lanzamiento": "17/01/2026 15:00"
    },
    {
        "id": 1768626038,
        "fecha_generacion": "2026-01-17 01:58:57",
        "juego": "LOTO",
        "numeros": "[2, 5, 26, 27, 34, 41]",
        "sorteo_objetivo": 5375,
        "estado": "PENDIENTE",
        "aciertos": 0,
        "score_afinidad": 0.0,
        "hora_dia": 1,
        "algoritmo": "gaussiano_inteligente_v1",
        "nota_especial": "NORMAL",
        "fecha_lanzamiento": "18/01/2026 21:00"
    },
    {
        "id": 1768630285,
        "fecha_generacion": "2026-01-17 02:53:26",
        "juego": "LOTO3",
        "numeros": "[0, 7, 9]",
        "sorteo_objetivo": 23998,
        "estado": "PENDIENTE",
        "aciertos": 0,
        "score_afinidad": 6.1,
        "hora_dia": 2,
        "algoritmo": "oraculo_neural_v4",
        "nota_especial": "NORMAL",
        "fecha_lanzamiento": "17/01/2026 14:00"
    },
    {
        "id": 1768625677,
        "fecha_generacion": "2026-01-17 01:36:28",
        "juego": "LOTO3",
        "numeros": "[0, 7, 9]",
        "sorteo_objetivo": 23998,
        "estado": "PENDIENTE",
        "aciertos": 0,
        "score_afinidad": 64.73,
        "hora_dia": 1,
        "algoritmo": "consenso_meritocratico_v2",
        "nota_especial": "🔥 ALTA CONFIANZA",
        "fecha_lanzamiento": "17/01/2026 14:00"
    },
    {
        "id": 1768618669,
        "fecha_generacion": "2026-01-16 23:40:30",
        "juego": "LOTO",
        "numeros": "[3, 14, 17, 22, 23, 38]",
        "sorteo_objetivo": 5375,
        "estado": "PENDIENTE",
        "aciertos": 0,
        "score_afinidad": 5.95,
        "hora_dia": 23,
        "algoritmo": "oraculo_neural_v3",
        "nota_especial": "NORMAL",
        "fecha_lanzamiento": "18/01/2026 21:00"
    },
    {
        "id": 1768625747,
        "fecha_generacion": "2026-01-17 01:36:28",
        "juego": "RACHA",
        "numeros": "[1, 2, 3, 4, 8, 13, 15, 17, 18, 19]",
        "sorteo_objetivo": 10301,
        "estado": "PENDIENTE",
        "aciertos": 0,
        "score_afinidad": 7.3,
        "hora_dia": 1,
        "algoritmo": "oraculo_neural_v4",
        "nota_especial": "NORMAL",
        "fecha_lanzamiento": "17/01/2026 15:00"
    },
    {
        "id": 1768630365,
        "fecha_generacion": "2026-01-17 02:53:26",
        "juego": "RACHA",
        "numeros": "[1, 2, 3, 4, 8, 13, 15, 17, 18, 19]",
        "sorteo_objetivo": 10301,
        "estado": "PENDIENTE",
        "aciertos": 0,
        "score_afinidad": 7.3,
        "hora_dia": 2,
        "algoritmo": "oraculo_neural_v4",
        "nota_especial": "NORMAL",
        "fecha_lanzamiento": "17/01/2026 15:00"
    },
    {
        "id": 1768625627,
        "fecha_generacion": "2026-01-17 01:36:28",
        "juego": "LOTO",
        "numeros": "[7, 14, 22, 29, 31, 32]",
        "sorteo_objetivo": 5375,
        "estado": "PENDIENTE",
        "aciertos": 0,
        "score_afinidad": 5.95,
        "hora_dia": 1,
        "algoritmo": "oraculo_neural_v3",
        "nota_especial": "NORMAL",
        "fecha_lanzamiento": "18/01/2026 21:00"
    },
    {
        "id": 1768630245,
        "fecha_generacion": "2026-01-17 02:53:26",
        "juego": "LOTO",
        "numeros": "[10, 12, 13, 17, 26, 37]",
        "sorteo_objetivo": 5375,
        "estado": "PENDIENTE",
        "aciertos": 0,
        "score_afinidad": 5.95,
        "hora_dia": 2,
        "algoritmo": "oraculo_neural_v3",
        "nota_especial": "NORMAL",
        "fecha_lanzamiento": "18/01/2026 21:00"
    },
    {
        "id": 1768622351,
        "fecha_generacion": "2026-01-17 00:47:31",
        "juego": "LOTO3",
        "numeros": "[3, 8, 9]",
        "sorteo_objetivo": 23998,
        "estado": "PENDIENTE",
        "aciertos": 0,
        "score_afinidad": 0.0,
        "hora_dia": 0,
        "algoritmo": "forense_biometrico_v1",
        "nota_especial": "NORMAL",
        "fecha_lanzamiento": "17/01/2026 14:00"
    },
    {
        "id": 1768636038,
        "fecha_generacion": "2026-01-17 04:28:29",
        "fecha_lanzamiento": "17/01/2026 14:00",
        "juego": "LOTO4",
        "numeros": [
            1,
            5,
            10,
            11
        ],
        "sorteo_objetivo": 11568,
        "estado": "PENDIENTE",
        "aciertos": 0,
        "score_afinidad": 50.65,
        "hora_dia": 4,
        "algoritmo": "consenso_meritocratico_v2",
        "nota_especial": "🔥 ALTA CONFIANZA"
    },
    {
        "id": 1768633050,
        "fecha_generacion": "2026-01-17 03:38:01",
        "fecha_lanzamiento": "17/01/2026 15:00",
        "juego": "RACHA",
        "numeros": [
            1,
            2,
            5,
            7,
            8,
            13,
            14,
            15,
            17,
            18
        ],
        "sorteo_objetivo": 10301,
        "estado": "PENDIENTE",
        "aciertos": 0,
        "score_afinidad": 74.8,
        "hora_dia": 3,
        "algoritmo": "consenso_meritocratico_v2",
        "nota_especial": "🔥 ALTA CONFIANZA"
    },
    {
        "id": 1768633040,
        "fecha_generacion": "2026-01-17 03:38:01",
        "fecha_lanzamiento": "17/01/2026 15:00",
        "juego": "RACHA",
        "numeros": [
            1,
            2,
            3,
            4,
            8,
            13,
            15,
            17,
            18,
            19
        ],
        "sorteo_objetivo": 10301,
        "estado": "PENDIENTE",
        "aciertos": 0,
        "score_afinidad": 7.3,
        "hora_dia": 3,
        "algoritmo": "oraculo_neural_v4",
        "nota_especial": "NORMAL"
    },
    {
        "id": 1768634176,
        "fecha_generacion": "2026-01-17 03:58:57",
        "fecha_lanzamiento": "18/01/2026 21:00",
        "juego": "LOTO",
        "numeros": [
            2,
            3,
            17,
            26,
            36,
            39
        ],
        "sorteo_objetivo": 5375,
        "estado": "PENDIENTE",
        "aciertos": 0,
        "score_afinidad": 5.95,
        "hora_dia": 3,
        "algoritmo": "oraculo_neural_v3",
        "nota_especial": "NORMAL"
    },
    {
        "id": 1768634909,
        "fecha_generacion": "2026-01-17 04:28:29",
        "fecha_lanzamiento": "18/01/2026 21:00",
        "juego": "LOTO",
        "numeros": [
            7,
            13,
            28,
            30,
            31,
            34
        ],
        "sorteo_objetivo": 5375,
        "estado": "PENDIENTE",
        "aciertos": 0,
        "score_afinidad": 0.0,
        "hora_dia": 4,
        "algoritmo": "forense_biometrico_v1",
        "nota_especial": "NORMAL"
    },
    {
        "id": 1768635968,
        "fecha_generacion": "2026-01-17 04:28:29",
        "fecha_lanzamiento": "18/01/2026 21:00",
        "juego": "LOTO",
        "numeros": [
            8,
            15,
            18,
            29,
            33,
            37
        ],
        "sorteo_objetivo": 5375,
        "estado": "PENDIENTE",
        "aciertos": 0,
        "score_afinidad": 34.73,
        "hora_dia": 4,
        "algoritmo": "consenso_meritocratico_v2",
        "nota_especial": "🔥 ALTA CONFIANZA"
    },
    {
        "id": 1768634537,
        "fecha_generacion": "2026-01-17 03:58:57",
        "fecha_lanzamiento": "17/01/2026 15:00",
        "juego": "RACHA",
        "numeros": [
            2,
            5,
            7,
            8,
            9,
            10,
            11,
            14,
            15,
            20
        ],
        "sorteo_objetivo": 10301,
        "estado": "PENDIENTE",
        "aciertos": 0,
        "score_afinidad": 0.0,
        "hora_dia": 3,
        "algoritmo": "forense_biometrico_v1",
        "nota_especial": "NORMAL"
    },
    {
        "id": 1768636903,
        "fecha_generacion": "2026-01-17 04:43:34",
        "fecha_lanzamiento": "17/01/2026 14:00",
        "juego": "LOTO3",
        "numeros": [
            0,
            7,
            9
        ],
        "sorteo_objetivo": 23998,
        "estado": "PENDIENTE",
        "aciertos": 0,
        "score_afinidad": 58.32,
        "hora_dia": 4,
        "algoritmo": "consenso_meritocratico_v2",
        "nota_especial": "🔥 ALTA CONFIANZA"
    },
    {
        "id": 1768636863,
        "fecha_generacion": "2026-01-17 04:43:34",
        "fecha_lanzamiento": "18/01/2026 21:00",
        "juego": "LOTO",
        "numeros": [
            1,
            13,
            15,
            29,
            33,
            35
        ],
        "sorteo_objetivo": 5375,
        "estado": "PENDIENTE",
        "aciertos": 0,
        "score_afinidad": 19.05,
        "hora_dia": 4,
        "algoritmo": "oraculo_neural_v4",
        "nota_especial": "NORMAL"
    },
    {
        "id": 1768635998,
        "fecha_generacion": "2026-01-17 04:28:29",
        "fecha_lanzamiento": "17/01/2026 14:00",
        "juego": "LOTO3",
        "numeros": [
            0,
            7,
            9
        ],
        "sorteo_objetivo": 23998,
        "estado": "PENDIENTE",
        "aciertos": 0,
        "score_afinidad": 67.94,
        "hora_dia": 4,
        "algoritmo": "consenso_meritocratico_v2",
        "nota_especial": "🔥 ALTA CONFIANZA"
    },
    {
        "id": 1768633137,
        "fecha_generacion": "2026-01-17 03:58:57",
        "fecha_lanzamiento": "18/01/2026 21:00",
        "juego": "LOTO",
        "numeros": [
            6,
            11,
            20,
            30,
            31,
            41
        ],
        "sorteo_objetivo": 5375,
        "estado": "PENDIENTE",
        "aciertos": 0,
        "score_afinidad": 0.0,
        "hora_dia": 3,
        "algoritmo": "forense_biometrico_v1",
        "nota_especial": "NORMAL"
    },
    {
        "id": 1768635814,
        "fecha_generacion": "2026-01-17 04:43:34",
        "fecha_lanzamiento": "18/01/2026 21:00",
        "juego": "LOTO",
        "numeros": [
            5,
            14,
            18,
            19,
            32,
            41
        ],
        "sorteo_objetivo": 5375,
        "estado": "PENDIENTE",
        "aciertos": 0,
        "score_afinidad": 0.0,
        "hora_dia": 4,
        "algoritmo": "forense_biometrico_v1",
        "nota_especial": "NORMAL"
    },
    {
        "id": 1768636943,
        "fecha_generacion": "2026-01-17 04:43:34",
        "fecha_lanzamiento": "17/01/2026 14:00",
        "juego": "LOTO4",
        "numeros": [
            9,
            17,
            22,
            23
        ],
        "sorteo_objetivo": 11568,
        "estado": "PENDIENTE",
        "aciertos": 0,
        "score_afinidad": 52.27,
        "hora_dia": 4,
        "algoritmo": "consenso_meritocratico_v2",
        "nota_especial": "🔥 ALTA CONFIANZA"
    },
    {
        "id": 1768632940,
        "fecha_generacion": "2026-01-17 03:38:01",
        "fecha_lanzamiento": "18/01/2026 21:00",
        "juego": "LOTO",
        "numeros": [
            14,
            15,
            19,
            27,
            29,
            33
        ],
        "sorteo_objetivo": 5375,
        "estado": "PENDIENTE",
        "aciertos": 0,
        "score_afinidad": 34.19,
        "hora_dia": 3,
        "algoritmo": "consenso_meritocratico_v2",
        "nota_especial": "🔥 ALTA CONFIANZA"
    },
    {
        "id": 1768636028,
        "fecha_generacion": "2026-01-17 04:28:29",
        "fecha_lanzamiento": "17/01/2026 14:00",
        "juego": "LOTO4",
        "numeros": [
            1,
            5,
            9,
            16
        ],
        "sorteo_objetivo": 11568,
        "estado": "PENDIENTE",
        "aciertos": 0,
        "score_afinidad": 13.45,
        "hora_dia": 4,
        "algoritmo": "oraculo_neural_v4",
        "nota_especial": "NORMAL"
    },
    {
        "id": 1768632970,
        "fecha_generacion": "2026-01-17 03:38:01",
        "fecha_lanzamiento": "17/01/2026 14:00",
        "juego": "LOTO3",
        "numeros": [
            0,
            7,
            9
        ],
        "sorteo_objetivo": 23998,
        "estado": "PENDIENTE",
        "aciertos": 0,
        "score_afinidad": 61.53,
        "hora_dia": 3,
        "algoritmo": "consenso_meritocratico_v2",
        "nota_especial": "🔥 ALTA CONFIANZA"
    },
    {
        "id": 1768633238,
        "fecha_generacion": "2026-01-17 03:58:57",
        "fecha_lanzamiento": "18/01/2026 21:00",
        "juego": "LOTO",
        "numeros": [
            4,
            12,
            19,
            23,
            30,
            31
        ],
        "sorteo_objetivo": 5375,
        "estado": "PENDIENTE",
        "aciertos": 0,
        "score_afinidad": 0.0,
        "hora_dia": 3,
        "algoritmo": "gaussiano_inteligente_v1",
        "nota_especial": "NORMAL"
    },
    {
        "id": 1768633837,
        "fecha_generacion": "2026-01-17 03:58:57",
        "fecha_lanzamiento": "17/01/2026 14:00",
        "juego": "LOTO3",
        "numeros": [
            1,
            4,
            5
        ],
        "sorteo_objetivo": 23998,
        "estado": "PENDIENTE",
        "aciertos": 0,
        "score_afinidad": 0.0,
        "hora_dia": 3,
        "algoritmo": "forense_biometrico_v1",
        "nota_especial": "NORMAL"
    },
    {
        "id": 1768636309,
        "fecha_generacion": "2026-01-17 04:28:29",
        "fecha_lanzamiento": "17/01/2026 15:00",
        "juego": "RACHA",
        "numeros": [
            3,
            4,
            5,
            6,
            8,
            14,
            15,
            17,
            19,
            20
        ],
        "sorteo_objetivo": 10301,
        "estado": "PENDIENTE",
        "aciertos": 0,
        "score_afinidad": 0.0,
        "hora_dia": 4,
        "algoritmo": "forense_biometrico_v1",
        "nota_especial": "NORMAL"
    },
    {
        "id": 1768632083,
        "fecha_generacion": "2026-01-17 03:38:01",
        "fecha_lanzamiento": "18/01/2026 21:00",
        "juego": "LOTO",
        "numeros": [
            8,
            11,
            23,
            24,
            27,
            34
        ],
        "sorteo_objetivo": 5375,
        "estado": "PENDIENTE",
        "aciertos": 0,
        "score_afinidad": 0.0,
        "hora_dia": 3,
        "algoritmo": "delta_dna_v1",
        "nota_especial": "NORMAL"
    },
    {
        "id": 1768632990,
        "fecha_generacion": "2026-01-17 03:38:01",
        "fecha_lanzamiento": "17/01/2026 14:00",
        "juego": "LOTO4",
        "numeros": [
            17,
            19,
            21,
            22
        ],
        "sorteo_objetivo": 11568,
        "estado": "PENDIENTE",
        "aciertos": 0,
        "score_afinidad": 3.25,
        "hora_dia": 3,
        "algoritmo": "oraculo_neural_v3",
        "nota_especial": "NORMAL"
    },
    {
        "id": 1768631982,
        "fecha_generacion": "2026-01-17 03:38:01",
        "fecha_lanzamiento": "18/01/2026 21:00",
        "juego": "LOTO",
        "numeros": [
            4,
            11,
            19,
            20,
            28,
            37
        ],
        "sorteo_objetivo": 5375,
        "estado": "PENDIENTE",
        "aciertos": 0,
        "score_afinidad": 0.0,
        "hora_dia": 3,
        "algoritmo": "gaussiano_inteligente_v1",
        "nota_especial": "NORMAL"
    },
    {
        "id": 1768632881,
        "fecha_generacion": "2026-01-17 03:38:01",
        "fecha_lanzamiento": "17/01/2026 14:00",
        "juego": "LOTO4",
        "numeros": [
            5,
            9,
            10,
            13
        ],
        "sorteo_objetivo": 11568,
        "estado": "PENDIENTE",
        "aciertos": 0,
        "score_afinidad": 0.0,
        "hora_dia": 3,
        "algoritmo": "forense_biometrico_v1",
        "nota_especial": "NORMAL"
    },
    {
        "id": 1768633010,
        "fecha_generacion": "2026-01-17 03:38:01",
        "fecha_lanzamiento": "17/01/2026 14:00",
        "juego": "LOTO4",
        "numeros": [
            17,
            19,
            21,
            22
        ],
        "sorteo_objetivo": 11568,
        "estado": "PENDIENTE",
        "aciertos": 0,
        "score_afinidad": 45.79,
        "hora_dia": 3,
        "algoritmo": "consenso_meritocratico_v2",
        "nota_especial": "🔥 ALTA CONFIANZA"
    },
    {
        "id": 1768634306,
        "fecha_generacion": "2026-01-17 03:58:57",
        "fecha_lanzamiento": "17/01/2026 15:00",
        "juego": "RACHA",
        "numeros": [
            1,
            3,
            4,
            5,
            7,
            8,
            10,
            13,
            17,
            20
        ],
        "sorteo_objetivo": 10301,
        "estado": "PENDIENTE",
        "aciertos": 0,
        "score_afinidad": 66.81,
        "hora_dia": 3,
        "algoritmo": "consenso_meritocratico_v2",
        "nota_especial": "🔥 ALTA CONFIANZA"
    },
    {
        "id": 1768636963,
        "fecha_generacion": "2026-01-17 04:43:34",
        "fecha_lanzamiento": "17/01/2026 15:00",
        "juego": "RACHA",
        "numeros": [
            1,
            2,
            3,
            4,
            8,
            9,
            13,
            14,
            17,
            20
        ],
        "sorteo_objetivo": 10301,
        "estado": "PENDIENTE",
        "aciertos": 0,
        "score_afinidad": 4.9,
        "hora_dia": 4,
        "algoritmo": "oraculo_neural_v3",
        "nota_especial": "NORMAL"
    },
    {
        "id": 1768634246,
        "fecha_generacion": "2026-01-17 03:58:57",
        "fecha_lanzamiento": "17/01/2026 14:00",
        "juego": "LOTO4",
        "numeros": [
            3,
            4,
            21,
            23
        ],
        "sorteo_objetivo": 11568,
        "estado": "PENDIENTE",
        "aciertos": 0,
        "score_afinidad": 3.25,
        "hora_dia": 3,
        "algoritmo": "oraculo_neural_v3",
        "nota_especial": "NORMAL"
    },
    {
        "id": 1768634226,
        "fecha_generacion": "2026-01-17 03:58:57",
        "fecha_lanzamiento": "17/01/2026 14:00",
        "juego": "LOTO3",
        "numeros": [
            0,
            7,
            9
        ],
        "sorteo_objetivo": 23998,
        "estado": "PENDIENTE",
        "aciertos": 0,
        "score_afinidad": 58.32,
        "hora_dia": 3,
        "algoritmo": "consenso_meritocratico_v2",
        "nota_especial": "🔥 ALTA CONFIANZA"
    },
    {
        "id": 1768636814,
        "fecha_generacion": "2026-01-17 04:43:34",
        "fecha_lanzamiento": "17/01/2026 14:00",
        "juego": "LOTO4",
        "numeros": [
            1,
            18,
            19,
            23
        ],
        "sorteo_objetivo": 11568,
        "estado": "PENDIENTE",
        "aciertos": 0,
        "score_afinidad": 0.0,
        "hora_dia": 4,
        "algoritmo": "forense_biometrico_v1",
        "nota_especial": "NORMAL"
    },
    {
        "id": 1768636973,
        "fecha_generacion": "2026-01-17 04:43:34",
        "fecha_lanzamiento": "17/01/2026 15:00",
        "juego": "RACHA",
        "numeros": [
            1,
            2,
            3,
            4,
            8,
            13,
            15,
            17,
            18,
            19
        ],
        "sorteo_objetivo": 10301,
        "estado": "PENDIENTE",
        "aciertos": 0,
        "score_afinidad": 7.3,
        "hora_dia": 4,
        "algoritmo": "oraculo_neural_v4",
        "nota_especial": "NORMAL"
    },
    {
        "id": 1768634266,
        "fecha_generacion": "2026-01-17 03:58:57",
        "fecha_lanzamiento": "17/01/2026 14:00",
        "juego": "LOTO4",
        "numeros": [
            3,
            5,
            9,
            23
        ],
        "sorteo_objetivo": 11568,
        "estado": "PENDIENTE",
        "aciertos": 0,
        "score_afinidad": 47.02,
        "hora_dia": 3,
        "algoritmo": "consenso_meritocratico_v2",
        "nota_especial": "🔥 ALTA CONFIANZA"
    },
    {
        "id": 1768631881,
        "fecha_generacion": "2026-01-17 03:38:01",
        "fecha_lanzamiento": "18/01/2026 21:00",
        "juego": "LOTO",
        "numeros": [
            2,
            18,
            20,
            21,
            29,
            41
        ],
        "sorteo_objetivo": 5375,
        "estado": "PENDIENTE",
        "aciertos": 0,
        "score_afinidad": 0.0,
        "hora_dia": 3,
        "algoritmo": "forense_biometrico_v1",
        "nota_especial": "NORMAL"
    },
    {
        "id": 1768636016,
        "fecha_generacion": "2026-01-17 04:43:34",
        "fecha_lanzamiento": "18/01/2026 21:00",
        "juego": "LOTO",
        "numeros": [
            2,
            13,
            14,
            21,
            24,
            31
        ],
        "sorteo_objetivo": 5375,
        "estado": "PENDIENTE",
        "aciertos": 0,
        "score_afinidad": 0.0,
        "hora_dia": 4,
        "algoritmo": "delta_dna_v1",
        "nota_especial": "NORMAL"
    },
    {
        "id": 1768634196,
        "fecha_generacion": "2026-01-17 03:58:57",
        "fecha_lanzamiento": "18/01/2026 21:00",
        "juego": "LOTO",
        "numeros": [
            13,
            27,
            29,
            34,
            35,
            39
        ],
        "sorteo_objetivo": 5375,
        "estado": "PENDIENTE",
        "aciertos": 0,
        "score_afinidad": 30.64,
        "hora_dia": 3,
        "algoritmo": "consenso_meritocratico_v2",
        "nota_especial": "🔥 ALTA CONFIANZA"
    },
    {
        "id": 1768634256,
        "fecha_generacion": "2026-01-17 03:58:57",
        "fecha_lanzamiento": "17/01/2026 14:00",
        "juego": "LOTO4",
        "numeros": [
            1,
            5,
            9,
            16
        ],
        "sorteo_objetivo": 11568,
        "estado": "PENDIENTE",
        "aciertos": 0,
        "score_afinidad": 13.45,
        "hora_dia": 3,
        "algoritmo": "oraculo_neural_v4",
        "nota_especial": "NORMAL"
    },
    {
        "id": 1768635988,
        "fecha_generacion": "2026-01-17 04:28:29",
        "fecha_lanzamiento": "17/01/2026 14:00",
        "juego": "LOTO3",
        "numeros": [
            0,
            7,
            9
        ],
        "sorteo_objetivo": 23998,
        "estado": "PENDIENTE",
        "aciertos": 0,
        "score_afinidad": 6.1,
        "hora_dia": 4,
        "algoritmo": "oraculo_neural_v4",
        "nota_especial": "NORMAL"
    },
    {
        "id": 1768635111,
        "fecha_generacion": "2026-01-17 04:28:29",
        "fecha_lanzamiento": "18/01/2026 21:00",
        "juego": "LOTO",
        "numeros": [
            5,
            21,
            26,
            30,
            31,
            34
        ],
        "sorteo_objetivo": 5375,
        "estado": "PENDIENTE",
        "aciertos": 0,
        "score_afinidad": 0.0,
        "hora_dia": 4,
        "algoritmo": "delta_dna_v1",
        "nota_especial": "NORMAL"
    },
    {
        "id": 1768635609,
        "fecha_generacion": "2026-01-17 04:28:29",
        "fecha_lanzamiento": "17/01/2026 14:00",
        "juego": "LOTO3",
        "numeros": [
            5,
            6,
            9
        ],
        "sorteo_objetivo": 23998,
        "estado": "PENDIENTE",
        "aciertos": 0,
        "score_afinidad": 0.0,
        "hora_dia": 4,
        "algoritmo": "forense_biometrico_v1",
        "nota_especial": "NORMAL"
    },
    {
        "id": 1768636923,
        "fecha_generacion": "2026-01-17 04:43:34",
        "fecha_lanzamiento": "17/01/2026 14:00",
        "juego": "LOTO4",
        "numeros": [
            9,
            17,
            22,
            23
        ],
        "sorteo_objetivo": 11568,
        "estado": "PENDIENTE",
        "aciertos": 0,
        "score_afinidad": 3.25,
        "hora_dia": 4,
        "algoritmo": "oraculo_neural_v3",
        "nota_especial": "NORMAL"
    },
    {
        "id": 1768632581,
        "fecha_generacion": "2026-01-17 03:38:01",
        "fecha_lanzamiento": "17/01/2026 14:00",
        "juego": "LOTO3",
        "numeros": [
            3,
            8,
            9
        ],
        "sorteo_objetivo": 23998,
        "estado": "PENDIENTE",
        "aciertos": 0,
        "score_afinidad": 0.0,
        "hora_dia": 3,
        "algoritmo": "forense_biometrico_v1",
        "nota_especial": "NORMAL"
    },
    {
        "id": 1768633339,
        "fecha_generacion": "2026-01-17 03:58:57",
        "fecha_lanzamiento": "18/01/2026 21:00",
        "juego": "LOTO",
        "numeros": [
            2,
            13,
            25,
            34,
            37,
            38
        ],
        "sorteo_objetivo": 5375,
        "estado": "PENDIENTE",
        "aciertos": 0,
        "score_afinidad": 0.0,
        "hora_dia": 3,
        "algoritmo": "delta_dna_v1",
        "nota_especial": "NORMAL"
    },
    {
        "id": 1768633440,
        "fecha_generacion": "2026-01-17 03:58:57",
        "fecha_lanzamiento": "18/01/2026 21:00",
        "juego": "LOTO",
        "numeros": [
            8,
            21,
            27,
            29,
            37,
            39
        ],
        "sorteo_objetivo": 5375,
        "estado": "PENDIENTE",
        "aciertos": 0,
        "score_afinidad": 0.0,
        "hora_dia": 3,
        "algoritmo": "markov_chain_v1",
        "nota_especial": "NORMAL"
    },
    {
        "id": 1768632920,
        "fecha_generacion": "2026-01-17 03:38:01",
        "fecha_lanzamiento": "18/01/2026 21:00",
        "juego": "LOTO",
        "numeros": [
            3,
            14,
            19,
            31,
            32,
            38
        ],
        "sorteo_objetivo": 5375,
        "estado": "PENDIENTE",
        "aciertos": 0,
        "score_afinidad": 5.95,
        "hora_dia": 3,
        "algoritmo": "oraculo_neural_v3",
        "nota_especial": "NORMAL"
    },
    {
        "id": 1768632184,
        "fecha_generacion": "2026-01-17 03:38:01",
        "fecha_lanzamiento": "18/01/2026 21:00",
        "juego": "LOTO",
        "numeros": [
            8,
            21,
            27,
            29,
            37,
            39
        ],
        "sorteo_objetivo": 5375,
        "estado": "PENDIENTE",
        "aciertos": 0,
        "score_afinidad": 0.0,
        "hora_dia": 3,
        "algoritmo": "markov_chain_v1",
        "nota_especial": "NORMAL"
    },
    {
        "id": 1768636058,
        "fecha_generacion": "2026-01-17 04:28:29",
        "fecha_lanzamiento": "17/01/2026 15:00",
        "juego": "RACHA",
        "numeros": [
            3,
            4,
            7,
            8,
            9,
            10,
            14,
            17,
            19,
            20
        ],
        "sorteo_objetivo": 10301,
        "estado": "PENDIENTE",
        "aciertos": 0,
        "score_afinidad": 4.9,
        "hora_dia": 4,
        "algoritmo": "oraculo_neural_v3",
        "nota_especial": "NORMAL"
    },
    {
        "id": 1768636514,
        "fecha_generacion": "2026-01-17 04:43:34",
        "fecha_lanzamiento": "17/01/2026 14:00",
        "juego": "LOTO3",
        "numeros": [
            1,
            4,
            5
        ],
        "sorteo_objetivo": 23998,
        "estado": "PENDIENTE",
        "aciertos": 0,
        "score_afinidad": 0.0,
        "hora_dia": 4,
        "algoritmo": "forense_biometrico_v1",
        "nota_especial": "NORMAL"
    },
    {
        "id": 1768636068,
        "fecha_generacion": "2026-01-17 04:28:29",
        "fecha_lanzamiento": "17/01/2026 15:00",
        "juego": "RACHA",
        "numeros": [
            1,
            2,
            3,
            4,
            8,
            13,
            15,
            17,
            18,
            19
        ],
        "sorteo_objetivo": 10301,
        "estado": "PENDIENTE",
        "aciertos": 0,
        "score_afinidad": 7.3,
        "hora_dia": 4,
        "algoritmo": "oraculo_neural_v4",
        "nota_especial": "NORMAL"
    },
    {
        "id": 1768634296,
        "fecha_generacion": "2026-01-17 03:58:57",
        "fecha_lanzamiento": "17/01/2026 15:00",
        "juego": "RACHA",
        "numeros": [
            1,
            2,
            3,
            4,
            8,
            13,
            15,
            17,
            18,
            19
        ],
        "sorteo_objetivo": 10301,
        "estado": "PENDIENTE",
        "aciertos": 0,
        "score_afinidad": 7.3,
        "hora_dia": 3,
        "algoritmo": "oraculo_neural_v4",
        "nota_especial": "NORMAL"
    },
    {
        "id": 1768636078,
        "fecha_generacion": "2026-01-17 04:28:29",
        "fecha_lanzamiento": "17/01/2026 15:00",
        "juego": "RACHA",
        "numeros": [
            3,
            4,
            7,
            8,
            10,
            14,
            15,
            17,
            19,
            20
        ],
        "sorteo_objetivo": 10301,
        "estado": "PENDIENTE",
        "aciertos": 0,
        "score_afinidad": 68.2,
        "hora_dia": 4,
        "algoritmo": "consenso_meritocratico_v2",
        "nota_especial": "🔥 ALTA CONFIANZA"
    },
    {
        "id": 1768636018,
        "fecha_generacion": "2026-01-17 04:28:29",
        "fecha_lanzamiento": "17/01/2026 14:00",
        "juego": "LOTO4",
        "numeros": [
            1,
            10,
            11,
            13
        ],
        "sorteo_objetivo": 11568,
        "estado": "PENDIENTE",
        "aciertos": 0,
        "score_afinidad": 3.25,
        "hora_dia": 4,
        "algoritmo": "oraculo_neural_v3",
        "nota_especial": "NORMAL"
    },
    {
        "id": 1768632960,
        "fecha_generacion": "2026-01-17 03:38:01",
        "fecha_lanzamiento": "17/01/2026 14:00",
        "juego": "LOTO3",
        "numeros": [
            0,
            7,
            9
        ],
        "sorteo_objetivo": 23998,
        "estado": "PENDIENTE",
        "aciertos": 0,
        "score_afinidad": 6.1,
        "hora_dia": 3,
        "algoritmo": "oraculo_neural_v4",
        "nota_especial": "NORMAL"
    },
    {
        "id": 1768637214,
        "fecha_generacion": "2026-01-17 04:43:34",
        "fecha_lanzamiento": "17/01/2026 15:00",
        "juego": "RACHA",
        "numeros": [
            3,
            4,
            5,
            8,
            11,
            12,
            15,
            18,
            19,
            20
        ],
        "sorteo_objetivo": 10301,
        "estado": "PENDIENTE",
        "aciertos": 0,
        "score_afinidad": 0.0,
        "hora_dia": 4,
        "algoritmo": "forense_biometrico_v1",
        "nota_especial": "NORMAL"
    },
    {
        "id": 1768636933,
        "fecha_generacion": "2026-01-17 04:43:34",
        "fecha_lanzamiento": "17/01/2026 14:00",
        "juego": "LOTO4",
        "numeros": [
            1,
            5,
            9,
            16
        ],
        "sorteo_objetivo": 11568,
        "estado": "PENDIENTE",
        "aciertos": 0,
        "score_afinidad": 13.45,
        "hora_dia": 4,
        "algoritmo": "oraculo_neural_v4",
        "nota_especial": "NORMAL"
    },
    {
        "id": 1768635915,
        "fecha_generacion": "2026-01-17 04:43:34",
        "fecha_lanzamiento": "18/01/2026 21:00",
        "juego": "LOTO",
        "numeros": [
            9,
            10,
            19,
            26,
            28,
            41
        ],
        "sorteo_objetivo": 5375,
        "estado": "PENDIENTE",
        "aciertos": 0,
        "score_afinidad": 0.0,
        "hora_dia": 4,
        "algoritmo": "gaussiano_inteligente_v1",
        "nota_especial": "NORMAL"
    },
    {
        "id": 1768634286,
        "fecha_generacion": "2026-01-17 03:58:57",
        "fecha_lanzamiento": "17/01/2026 15:00",
        "juego": "RACHA",
        "numeros": [
            3,
            4,
            5,
            7,
            8,
            10,
            11,
            12,
            17,
            20
        ],
        "sorteo_objetivo": 10301,
        "estado": "PENDIENTE",
        "aciertos": 0,
        "score_afinidad": 5.9,
        "hora_dia": 3,
        "algoritmo": "oraculo_neural_v3",
        "nota_especial": "NORMAL"
    },
    {
        "id": 1768635212,
        "fecha_generacion": "2026-01-17 04:28:29",
        "fecha_lanzamiento": "18/01/2026 21:00",
        "juego": "LOTO",
        "numeros": [
            8,
            21,
            27,
            29,
            37,
            39
        ],
        "sorteo_objetivo": 5375,
        "estado": "PENDIENTE",
        "aciertos": 0,
        "score_afinidad": 0.0,
        "hora_dia": 4,
        "algoritmo": "markov_chain_v1",
        "nota_especial": "NORMAL"
    },
    {
        "id": 1768636117,
        "fecha_generacion": "2026-01-17 04:43:34",
        "fecha_lanzamiento": "18/01/2026 21:00",
        "juego": "LOTO",
        "numeros": [
            8,
            21,
            27,
            29,
            37,
            39
        ],
        "sorteo_objetivo": 5375,
        "estado": "PENDIENTE",
        "aciertos": 0,
        "score_afinidad": 0.0,
        "hora_dia": 4,
        "algoritmo": "markov_chain_v1",
        "nota_especial": "NORMAL"
    },
    {
        "id": 1768634186,
        "fecha_generacion": "2026-01-17 03:58:57",
        "fecha_lanzamiento": "18/01/2026 21:00",
        "juego": "LOTO",
        "numeros": [
            1,
            13,
            15,
            29,
            33,
            35
        ],
        "sorteo_objetivo": 5375,
        "estado": "PENDIENTE",
        "aciertos": 0,
        "score_afinidad": 19.05,
        "hora_dia": 3,
        "algoritmo": "oraculo_neural_v4",
        "nota_especial": "NORMAL"
    },
    {
        "id": 1768635010,
        "fecha_generacion": "2026-01-17 04:28:29",
        "fecha_lanzamiento": "18/01/2026 21:00",
        "juego": "LOTO",
        "numeros": [
            6,
            8,
            11,
            28,
            29,
            37
        ],
        "sorteo_objetivo": 5375,
        "estado": "PENDIENTE",
        "aciertos": 0,
        "score_afinidad": 0.0,
        "hora_dia": 4,
        "algoritmo": "gaussiano_inteligente_v1",
        "nota_especial": "NORMAL"
    },
    {
        "id": 1768636853,
        "fecha_generacion": "2026-01-17 04:43:34",
        "fecha_lanzamiento": "18/01/2026 21:00",
        "juego": "LOTO",
        "numeros": [
            3,
            23,
            28,
            30,
            31,
            38
        ],
        "sorteo_objetivo": 5375,
        "estado": "PENDIENTE",
        "aciertos": 0,
        "score_afinidad": 5.95,
        "hora_dia": 4,
        "algoritmo": "oraculo_neural_v3",
        "nota_especial": "NORMAL"
    },
    {
        "id": 1768635909,
        "fecha_generacion": "2026-01-17 04:28:29",
        "fecha_lanzamiento": "17/01/2026 14:00",
        "juego": "LOTO4",
        "numeros": [
            1,
            2,
            15,
            23
        ],
        "sorteo_objetivo": 11568,
        "estado": "PENDIENTE",
        "aciertos": 0,
        "score_afinidad": 0.0,
        "hora_dia": 4,
        "algoritmo": "forense_biometrico_v1",
        "nota_especial": "NORMAL"
    },
    {
        "id": 1768632930,
        "fecha_generacion": "2026-01-17 03:38:01",
        "fecha_lanzamiento": "18/01/2026 21:00",
        "juego": "LOTO",
        "numeros": [
            1,
            13,
            15,
            29,
            33,
            35
        ],
        "sorteo_objetivo": 5375,
        "estado": "PENDIENTE",
        "aciertos": 0,
        "score_afinidad": 19.05,
        "hora_dia": 3,
        "algoritmo": "oraculo_neural_v4",
        "nota_especial": "NORMAL"
    },
    {
        "id": 1768633281,
        "fecha_generacion": "2026-01-17 03:38:01",
        "fecha_lanzamiento": "17/01/2026 15:00",
        "juego": "RACHA",
        "numeros": [
            4,
            5,
            6,
            8,
            9,
            10,
            13,
            17,
            19,
            20
        ],
        "sorteo_objetivo": 10301,
        "estado": "PENDIENTE",
        "aciertos": 0,
        "score_afinidad": 0.0,
        "hora_dia": 3,
        "algoritmo": "forense_biometrico_v1",
        "nota_especial": "NORMAL"
    },
    {
        "id": 1768636873,
        "fecha_generacion": "2026-01-17 04:43:34",
        "fecha_lanzamiento": "18/01/2026 21:00",
        "juego": "LOTO",
        "numeros": [
            8,
            10,
            24,
            30,
            35,
            39
        ],
        "sorteo_objetivo": 5375,
        "estado": "PENDIENTE",
        "aciertos": 0,
        "score_afinidad": 31.91,
        "hora_dia": 4,
        "algoritmo": "consenso_meritocratico_v2",
        "nota_especial": "🔥 ALTA CONFIANZA"
    },
    {
        "id": 1768636983,
        "fecha_generacion": "2026-01-17 04:43:34",
        "fecha_lanzamiento": "17/01/2026 15:00",
        "juego": "RACHA",
        "numeros": [
            1,
            2,
            3,
            4,
            8,
            13,
            14,
            17,
            19,
            20
        ],
        "sorteo_objetivo": 10301,
        "estado": "PENDIENTE",
        "aciertos": 0,
        "score_afinidad": 73.99,
        "hora_dia": 4,
        "algoritmo": "consenso_meritocratico_v2",
        "nota_especial": "🔥 ALTA CONFIANZA"
    },
    {
        "id": 1768634137,
        "fecha_generacion": "2026-01-17 03:58:57",
        "fecha_lanzamiento": "17/01/2026 14:00",
        "juego": "LOTO4",
        "numeros": [
            3,
            7,
            15,
            16
        ],
        "sorteo_objetivo": 11568,
        "estado": "PENDIENTE",
        "aciertos": 0,
        "score_afinidad": 0.0,
        "hora_dia": 3,
        "algoritmo": "forense_biometrico_v1",
        "nota_especial": "NORMAL"
    },
    {
        "id": 1768635948,
        "fecha_generacion": "2026-01-17 04:28:29",
        "fecha_lanzamiento": "18/01/2026 21:00",
        "juego": "LOTO",
        "numeros": [
            7,
            18,
            22,
            23,
            29,
            38
        ],
        "sorteo_objetivo": 5375,
        "estado": "PENDIENTE",
        "aciertos": 0,
        "score_afinidad": 5.95,
        "hora_dia": 4,
        "algoritmo": "oraculo_neural_v3",
        "nota_especial": "NORMAL"
    },
    {
        "id": 1768635958,
        "fecha_generacion": "2026-01-17 04:28:29",
        "fecha_lanzamiento": "18/01/2026 21:00",
        "juego": "LOTO",
        "numeros": [
            1,
            13,
            15,
            29,
            33,
            35
        ],
        "sorteo_objetivo": 5375,
        "estado": "PENDIENTE",
        "aciertos": 0,
        "score_afinidad": 19.05,
        "hora_dia": 4,
        "algoritmo": "oraculo_neural_v4",
        "nota_especial": "NORMAL"
    },
    {
        "id": 1768636893,
        "fecha_generacion": "2026-01-17 04:43:34",
        "fecha_lanzamiento": "17/01/2026 14:00",
        "juego": "LOTO3",
        "numeros": [
            0,
            7,
            9
        ],
        "sorteo_objetivo": 23998,
        "estado": "PENDIENTE",
        "aciertos": 0,
        "score_afinidad": 6.1,
        "hora_dia": 4,
        "algoritmo": "oraculo_neural_v4",
        "nota_especial": "NORMAL"
    },
    {
        "id": 1768633030,
        "fecha_generacion": "2026-01-17 03:38:01",
        "fecha_lanzamiento": "17/01/2026 15:00",
        "juego": "RACHA",
        "numeros": [
            1,
            2,
            5,
            7,
            8,
            13,
            14,
            15,
            16,
            18
        ],
        "sorteo_objetivo": 10301,
        "estado": "PENDIENTE",
        "aciertos": 0,
        "score_afinidad": 4.9,
        "hora_dia": 3,
        "algoritmo": "oraculo_neural_v3",
        "nota_especial": "NORMAL"
    },
    {
        "id": 1768633000,
        "fecha_generacion": "2026-01-17 03:38:01",
        "fecha_lanzamiento": "17/01/2026 14:00",
        "juego": "LOTO4",
        "numeros": [
            1,
            5,
            9,
            16
        ],
        "sorteo_objetivo": 11568,
        "estado": "PENDIENTE",
        "aciertos": 0,
        "score_afinidad": 13.45,
        "hora_dia": 3,
        "algoritmo": "oraculo_neural_v4",
        "nota_especial": "NORMAL"
    },
    {
        "id": 1768634216,
        "fecha_generacion": "2026-01-17 03:58:57",
        "fecha_lanzamiento": "17/01/2026 14:00",
        "juego": "LOTO3",
        "numeros": [
            0,
            7,
            9
        ],
        "sorteo_objetivo": 23998,
        "estado": "PENDIENTE",
        "aciertos": 0,
        "score_afinidad": 6.1,
        "hora_dia": 3,
        "algoritmo": "oraculo_neural_v4",
        "nota_especial": "NORMAL"
    }
]